logger_frame/fwork_init.py
logger_frame/init.py
logger_frame/log_guitest.py
logger_frame/logger.py
logger_easy-0.1.5.dist-info/METADATA
logger_easy-0.1.5.dist-info/WHEEL
logger_easy-0.1.5.dist-info/entry_points.txt
logger_easy-0.1.5.dist-info/top_level.txt
logger_easy-0.1.5.dist-info/RECORD
