Metadata-Version: 2.4
Name: logger_easy
Version: 0.1.5
Summary: loggingは難しいけどprintだと管理しにくいようなときの簡易ログライブラリです
